best_bottrop_garbage_collection_dates/__init__.py
best_bottrop_garbage_collection_dates/best_bottrop_garbage_collection_dates.py
best_bottrop_garbage_collection_dates/const.py
best_bottrop_garbage_collection_dates-1.0.1.dist-info/LICENSE
best_bottrop_garbage_collection_dates-1.0.1.dist-info/METADATA
best_bottrop_garbage_collection_dates-1.0.1.dist-info/WHEEL
best_bottrop_garbage_collection_dates-1.0.1.dist-info/top_level.txt
best_bottrop_garbage_collection_dates-1.0.1.dist-info/RECORD
