Metadata-Version: 2.1
Name: best_bottrop_garbage_collection_dates
Version: 1.0.1
Summary: A package to find the garbage collection dates in the city of Bottrop, Germany
Home-page: https://github.com/Nazze/best_bottrop_garbage_collection_dates
Author: Nazze
Project-URL: Bug Tracker, https://github.com/Nazze/best_bottrop_garbage_collection_dates/issues
Classifier: Programming Language :: Python :: 3
Classifier: License :: OSI Approved :: MIT License
Classifier: Operating System :: OS Independent
Requires-Python: >=3.6
License-File: LICENSE
